LICENSE
MANIFEST.in
README.md
RELEASING.md
setup.py
schemapi/__init__.py
schemapi/jsonschema.py
schemapi/trait_extractors.py
schemapi/version.py
schemapi.egg-info/PKG-INFO
schemapi.egg-info/SOURCES.txt
schemapi.egg-info/dependency_links.txt
schemapi.egg-info/top_level.txt
schemapi/schemas/vega-lite-v2.0.0.json
schemapi/schemas/vega-v3.0.0.json
schemapi/src/__init__.py
schemapi/src/jstraitlets.py
schemapi/src/tests/__init__.py
schemapi/src/tests/test_jstraitlets.py
schemapi/tests/__init__.py
schemapi/tests/_testcases.py
schemapi/tests/test_jsonschema.py
schemapi/tests/test_schemas.py
schemapi/tests/test_testcases.py
schemapi/utils/__init__.py
schemapi/utils/_save_module.py
schemapi/utils/core.py
schemapi/utils/dynimport.py
schemapi/utils/funccall.py
schemapi/utils/tests/__init__.py
schemapi/utils/tests/test_core.py
schemapi/utils/tests/test_dynimport.py
schemapi/utils/tests/test_save_module.py