Metadata-Version: 1.1
Name: schemapi
Version: 0.3.0
Summary: schemapi: generate Python APIs from JSONSchema specifications
Home-page: http://github.com/altair-viz/schemapi
Author: Jake VanderPlas
Author-email: jakevdp@uw.edu
License: BSD
Platform: OS Independent
Requires: jsonschema
Requires: traitlets
Requires: jinja2
